BochangTronJisuHuanjingDajianDeShizhanGongchengMoban/README.md
BochangTronJisuHuanjingDajianDeShizhanGongchengMoban/__init__.py
BochangTronJisuHuanjingDajianDeShizhanGongchengMoban/__main__.py
BochangTronJisuHuanjingDajianDeShizhanGongchengMoban/file.epub
BochangTronJisuHuanjingDajianDeShizhanGongchengMoban/index.html
BochangTronJisuHuanjingDajianDeShizhanGongchengMoban/css/__init__.py
BochangTronJisuHuanjingDajianDeShizhanGongchengMoban/css/annotations.css
BochangTronJisuHuanjingDajianDeShizhanGongchengMoban/css/main.css
BochangTronJisuHuanjingDajianDeShizhanGongchengMoban/css/normalize.css
BochangTronJisuHuanjingDajianDeShizhanGongchengMoban/css/popup.css
BochangTronJisuHuanjingDajianDeShizhanGongchengMoban/font/__init__.py
BochangTronJisuHuanjingDajianDeShizhanGongchengMoban/font/fontello.eot
BochangTronJisuHuanjingDajianDeShizhanGongchengMoban/font/fontello.svg
BochangTronJisuHuanjingDajianDeShizhanGongchengMoban/font/fontello.ttf
BochangTronJisuHuanjingDajianDeShizhanGongchengMoban/font/fontello.woff
BochangTronJisuHuanjingDajianDeShizhanGongchengMoban/img/__init__.py
BochangTronJisuHuanjingDajianDeShizhanGongchengMoban/img/annotator-glyph-sprite.png
BochangTronJisuHuanjingDajianDeShizhanGongchengMoban/img/annotator-icon-sprite.png
BochangTronJisuHuanjingDajianDeShizhanGongchengMoban/img/apple-touch-icon.png
BochangTronJisuHuanjingDajianDeShizhanGongchengMoban/img/cancelfullscreen.png
BochangTronJisuHuanjingDajianDeShizhanGongchengMoban/img/close.png
BochangTronJisuHuanjingDajianDeShizhanGongchengMoban/img/fullscreen.png
BochangTronJisuHuanjingDajianDeShizhanGongchengMoban/img/loader.gif
BochangTronJisuHuanjingDajianDeShizhanGongchengMoban/img/menu-icon.png
BochangTronJisuHuanjingDajianDeShizhanGongchengMoban/img/save.png
BochangTronJisuHuanjingDajianDeShizhanGongchengMoban/img/saved.png
BochangTronJisuHuanjingDajianDeShizhanGongchengMoban/img/settings-s.png
BochangTronJisuHuanjingDajianDeShizhanGongchengMoban/img/settings.png
bochang_tron_jisu_huanjing_dajian_de_shizhan_gongcheng_moban-2024.3.4.0.dist-info/METADATA
bochang_tron_jisu_huanjing_dajian_de_shizhan_gongcheng_moban-2024.3.4.0.dist-info/WHEEL
bochang_tron_jisu_huanjing_dajian_de_shizhan_gongcheng_moban-2024.3.4.0.dist-info/entry_points.txt
bochang_tron_jisu_huanjing_dajian_de_shizhan_gongcheng_moban-2024.3.4.0.dist-info/top_level.txt
bochang_tron_jisu_huanjing_dajian_de_shizhan_gongcheng_moban-2024.3.4.0.dist-info/RECORD
